{"name": "Alice", "dialogue": "Oh, have you guys heard about the new hiking trail that just opened up in the nearby mountains? It's supposed to be an amazing experience!"}
{"name": "Eva", "dialogue": "That sounds incredible! I've always wanted to explore more of nature. What made you decide to try it out?"}
{"name": "Alice", "dialogue": "Honestly, I was a bit hesitant at first, but"}
{"name": "Eva", "dialogue": "Aw, thank you! I'm glad I could inspire you to step out of your comfort zone. What did you think of the trail?"}
{"name": "Alice", "dialogue": "It was breathtaking! The views were stunning, and the sense of accomplishment when we reached the top was incredible."}
