{"name": "Eva", "dialogue": "You know, David, sometimes I feel like we're all just trying to make sense of this chaotic world."}
{"name": "David", "dialogue": "Ah, Eva, you always have a way of cutting through the noise and getting to the heart of things. I think that's what I love most about our conversations."}
{"name": "Eva", "dialogue": "And I love how your imagination runs wild! You always seem to be chasing after something new and exciting."}
{"name": "David", "dialogue": "(laughs) Yeah, maybe too excited sometimes! But it's exhilarating to explore all these creative possibilities. Don't you ever feel like that?"}
{"name": "Eva", "dialogue": "Oh, yes! Although sometimes it can be overwhelming, trying to keep up with your ideas. (smiling)"}
{"name": "David", "dialogue": "(laughs) Fair enough! I'm glad someone is keeping me grounded."}
