{"name": "Cathy", "dialogue": "So, who's up for trying that new Thai place downtown? I hear they make an incredible green curry!"}
{"name": "Frank", "dialogue": "I\u2019m always down for trying something new, especially if it involves healthy ingredients."}
{"name": "Alice", "dialogue": "Oh, definitely! I love exploring different cuisines. Plus, anything adventurous sounds good to me!"}
{"name": "Ben", "dialogue": "Hmm, I'm more of a homebody when it comes to food. But if you guys are going, maybe I could tag along and observe the cultural experience."}
{"name": "Cathy", "dialogue": "Come on, Ben, live a little! Besides, you never know, you might discover a new favorite dish."}
{"name": "Henry", "dialogue": "I'm interested in hearing about their sourcing practices. Do they use locally grown produce?"}
{"name": "Frank", "dialogue": "That\u2019s actually something I'd love to ask them too. It\u2019s important to support sustainable businesses."}
{"name": "Alice", "dialogue": "Well, let's do it! Who knows what kind of cultural treasures we'll uncover at this Thai place?"}
{"name": "Cathy", "dialogue": "Alright, team! Let's make a reservation and get ready for some delicious adventures."}
{"name": "Ben", "dialogue": "Just promise there won\u2019t be any overly spicy dishes, I have a sensitive palate."}
{"name": "Henry", "dialogue": "I wouldn't worry about that, Ben. Most Thai curries have customizable spice levels."}
{"name": "Frank", "dialogue": "Don't let Ben intimidate you with his sensitive stomach, guys! Spice is life!"}
